{
  "name": "Wholesome Street",
  "bio": "Providing bricks that will click tight, tight, tight! to those who are bricking bad",
  "profilePicture": "/profile-picture.jpg",
  "url": "https://wholesomestreet.com",
  "blog": false,
  "iconLinks": [
    {
      "id": "1728534577184",
      "icon": "instagram",
      "url": "https://instagram.com/thewholesomestreet"
    },
    {
      "id": "1728534577185",
      "icon": "facebook",
      "url": "https://facebook.com/thewholesomestreet"
    },
    {
      "id": "1757838290392",
      "icon": "x",
      "url": "https://x.com/wholesomestreet"
    },
    {
      "id": "1757838595400",
      "icon": "tiktok",
      "url": "https://tiktok.com/@thewholesomestreet"
    },
    {
      "id": "1757838698937",
      "icon": "email",
      "url": "mailto:say.hi@wholesomesteet.com"
    }
  ],
  "customLinks": [
    {
      "id": "1728534585738",
      "title": "Bricklink store",
      "url": "https://bricklink.wholesomestreet.com"
    },
    {
      "id": "1728534585739",
      "title": "Brick Owl store",
      "url": "https://brickowl.wholesomestreet.com"
    }
  ]
}
